wx_icons_humanity
