Metadata-Version: 2.1
Name: wx-icons-humanity
Version: 0.1.3
Summary: Humanity and Humanity Dark icon themes for wxPython 🐍
Home-page: https://github.com/domdfcoding/custom_wx_icons_humanity
Author: Dominic Davis-Foster
Author-email: dominic@davis-foster.co.uk
License: GNU General Public License v2 (GPLv2)
Project-URL: Documentation, https://custom_wx_icons_humanity.readthedocs.io
Project-URL: Issue_Tracker, https://github.com/domdfcoding/custom_wx_icons_humanity/issues
Project-URL: Source_Code, https://github.com/domdfcoding/custom_wx_icons_humanity
Keywords: wxpython,icons,iconset,humanity
Platform: Windows
Platform: macOS
Platform: Linux
Classifier: Development Status :: 3 - Alpha
Classifier: Environment :: X11 Applications :: GTK
Classifier: Intended Audience :: Developers
Classifier: License :: OSI Approved :: GNU General Public License v2 (GPLv2)
Classifier: Operating System :: OS Independent
Classifier: Operating System :: POSIX :: Linux
Classifier: Programming Language :: Python
Classifier: Programming Language :: Python :: 3 :: Only
Classifier: Programming Language :: Python :: 3.6
Classifier: Programming Language :: Python :: 3.7
Classifier: Programming Language :: Python :: 3.8
Classifier: Programming Language :: Python :: Implementation :: CPython
Classifier: Topic :: Desktop Environment :: Gnome
Classifier: Topic :: Software Development :: Libraries :: Python Modules
Classifier: Topic :: Software Development :: User Interfaces
Classifier: Typing :: Typed
Requires-Python: >=3.6
Provides-Extra: all
